.gitignore
LICENSE
README.rst
_config.yml
setup.py
JMRPi.Spark.Foundations.egg-info/PKG-INFO
JMRPi.Spark.Foundations.egg-info/SOURCES.txt
JMRPi.Spark.Foundations.egg-info/dependency_links.txt
JMRPi.Spark.Foundations.egg-info/requires.txt
JMRPi.Spark.Foundations.egg-info/top_level.txt
JMRPiFoundations/__init__.py
JMRPiFoundations/CLI/rpi-spark
JMRPiFoundations/CLI/rpi-spark3
JMRPiFoundations/CLI/rspk
JMRPiFoundations/CLI/rspk3
JMRPiFoundations/Devices/__init__.py
JMRPiFoundations/Devices/rpi_spark_z_1_0_0.py
JMRPiFoundations/Skeleton/RPiSpark.py
JMRPiFoundations/Skeleton/RPiSparkModule.py
JMRPiFoundations/Skeleton/RPiSparkProvider.py
JMRPiFoundations/Skeleton/__init__.py
JMRPiFoundations/Utiles/AvgCalculators.py
JMRPiFoundations/Utiles/DataFilters.py
JMRPiFoundations/Utiles/OSInfo.py
JMRPiFoundations/Utiles/__init__.py
dist/JMRPi.Spark.Foundations-1.0.2.tar.gz
dist/JMRPi.Spark.Foundations-1.0.3.tar.gz
dist/JMRPi.Spark.Foundations-1.0.4.tar.gz
examples/README.1st