Metadata-Version: 1.1
Name: JMRPi.Spark.Foundations
Version: 1.0.7
Summary: The Raspberry Pi Spark pHat board let you to easily develop interesting applications use the GPIO of Raspberry Pi. It included SSD1306 128x64 OLED, MPU6050 Sensor (Gyroscope, Accelerometer, Thermometer Sensor), 5 ways joystick, 2 action keys, 3.5mm stereo headphone jack, Speaker and 19 extended GPIO pads
Home-page: https://github.com/mobinrg/rpi_spark_foundation
Author: Kunpeng Zhang
Author-email: support@mobinrg.com
License: MIT
Keywords: development kitoledmonochrome greyscale colorssd1306mpu6050attitude shake motion gyroscope accelerometer thermometer sensorspi i2c 128x64key buttonsjoystick gameaudio speaker headset headphone earphonepwm tonemp3 wavegpio extended padspHATRaspberry Pi
Platform: Linux
Classifier: Development Status :: 4 - Beta
Classifier: Operating System :: POSIX :: Linux
Classifier: License :: OSI Approved :: MIT License
Classifier: Intended Audience :: Developers
Classifier: Programming Language :: Python :: 2.7
Classifier: Programming Language :: Python :: 3
Classifier: Topic :: Software Development
Classifier: Topic :: System :: Hardware
Classifier: Topic :: System :: Hardware :: Hardware Drivers
